yb_hello/__init__.py
yb_hello/yb_hello.py
yb_hello-1.0.0.dist-info/METADATA
yb_hello-1.0.0.dist-info/WHEEL
yb_hello-1.0.0.dist-info/top_level.txt
yb_hello-1.0.0.dist-info/RECORD
